BrainflowCyton/__init__.py
BrainflowCyton/eeg.py
BrainflowCyton/py.typed
brainflowcyton-0.2.2.dist-info/METADATA
brainflowcyton-0.2.2.dist-info/WHEEL
brainflowcyton-0.2.2.dist-info/licenses/LICENSE
brainflowcyton-0.2.2.dist-info/RECORD
