Metadata-Version: 2.4
Name: BrainflowCyton
Version: 0.2.2
Summary: Python wrapper for BrainFlow API + Cyton SDK for collecting realtime or offline (SDCard) EEG, EMG, EKG data.
Project-URL: Homepage, https://github.com/zeyus-research/BrainflowCytonEEGWrapper
Project-URL: Bug Tracker, https://github.com/zeyus-research/BrainflowCytonEEGWrapper/issues
Project-URL: Repository, https://github.com/zeyus-research/BrainflowCytonEEGWrapper
Author-email: zeyus <dev@zeyus.com>
License: MIT
License-File: LICENSE
Keywords: biosignals,brainflow,cyton,eeg,ekg,emg
Classifier: Development Status :: 4 - Beta
Classifier: Intended Audience :: Science/Research
Classifier: License :: OSI Approved :: MIT License
Classifier: Natural Language :: English
Classifier: Operating System :: OS Independent
Classifier: Operating System :: POSIX :: Linux
Classifier: Programming Language :: Python :: 3 :: Only
Classifier: Programming Language :: Python :: 3.9
Classifier: Programming Language :: Python :: 3.10
Classifier: Programming Language :: Python :: 3.11
Classifier: Programming Language :: Python :: 3.12
Classifier: Topic :: Scientific/Engineering :: Bio-Informatics
Classifier: Topic :: Scientific/Engineering :: Human Machine Interfaces
Classifier: Topic :: System :: Hardware
Classifier: Topic :: Utilities
Requires-Python: >=3.9
Requires-Dist: brainflow>=5.0.0
Requires-Dist: numpy>=1.24.0
Requires-Dist: pandas>=2.0.0
Requires-Dist: pyxdf>=1.16.0
Requires-Dist: samplerate>=0.2.0
Requires-Dist: scipy>=1.10.0
Provides-Extra: all
Requires-Dist: sounddevice>=0.4.6; extra == 'all'
Provides-Extra: audio
Requires-Dist: sounddevice>=0.4.6; extra == 'audio'
